otp_generate/__init__.py
otp_generate/main.py
otp_generate-0.0.6.dist-info/LICENSE
otp_generate-0.0.6.dist-info/METADATA
otp_generate-0.0.6.dist-info/WHEEL
otp_generate-0.0.6.dist-info/entry_points.txt
otp_generate-0.0.6.dist-info/top_level.txt
otp_generate-0.0.6.dist-info/RECORD
