Metadata-Version: 2.1
Name: otp_generate
Version: 0.0.6
Summary: A simple otp generate package
Home-page: https://github.com/MariMuthu15/otp-generate-package
Author: Marimuthu
Author-email: mahimari555@gmail.com
License: MIT
Classifier: Development Status :: 3 - Alpha
Classifier: Intended Audience :: Developers
Classifier: Topic :: Software Development :: Build Tools
Classifier: Programming Language :: Python :: 3
Classifier: License :: OSI Approved :: MIT License
Classifier: Operating System :: OS Independent
Classifier: Topic :: Software Development
Classifier: Topic :: Utilities
Requires-Python: >=3
License-File: LICENSE
